odoo/addons/account_invoice_refund_reason/README.rst
odoo/addons/account_invoice_refund_reason/__init__.py
odoo/addons/account_invoice_refund_reason/__manifest__.py
odoo/addons/account_invoice_refund_reason/data/account.move.refund.reason.csv
odoo/addons/account_invoice_refund_reason/i18n/account_invoice_refund_reason.pot
odoo/addons/account_invoice_refund_reason/i18n/de.po
odoo/addons/account_invoice_refund_reason/i18n/es.po
odoo/addons/account_invoice_refund_reason/i18n/hr.po
odoo/addons/account_invoice_refund_reason/i18n/it.po
odoo/addons/account_invoice_refund_reason/models/__init__.py
odoo/addons/account_invoice_refund_reason/models/account_move.py
odoo/addons/account_invoice_refund_reason/models/account_move_refund_reason.py
odoo/addons/account_invoice_refund_reason/readme/CONFIGURE.md
odoo/addons/account_invoice_refund_reason/readme/CONTRIBUTORS.md
odoo/addons/account_invoice_refund_reason/readme/DESCRIPTION.md
odoo/addons/account_invoice_refund_reason/readme/USAGE.md
odoo/addons/account_invoice_refund_reason/security/ir.model.access.csv
odoo/addons/account_invoice_refund_reason/static/description/icon.png
odoo/addons/account_invoice_refund_reason/static/description/index.html
odoo/addons/account_invoice_refund_reason/tests/__init__.py
odoo/addons/account_invoice_refund_reason/tests/test_account_invoice_refund_reason.py
odoo/addons/account_invoice_refund_reason/views/account_move_refund_reason_view.xml
odoo/addons/account_invoice_refund_reason/views/account_move_view.xml
odoo/addons/account_invoice_refund_reason/wizard/__init__.py
odoo/addons/account_invoice_refund_reason/wizard/account_move_reversal.py
odoo/addons/account_invoice_refund_reason/wizard/account_move_reversal_view.xml
odoo_addon_account_invoice_refund_reason-18.0.1.0.0.2.dist-info/METADATA
odoo_addon_account_invoice_refund_reason-18.0.1.0.0.2.dist-info/WHEEL
odoo_addon_account_invoice_refund_reason-18.0.1.0.0.2.dist-info/top_level.txt
odoo_addon_account_invoice_refund_reason-18.0.1.0.0.2.dist-info/RECORD
