Metadata-Version: 2.1
Name: odoo-addon-account_invoice_refund_reason
Version: 18.0.1.0.0.2
Requires-Python: >=3.10
Requires-Dist: odoo==18.0.*
Summary: Account Invoice Refund Reason.
Home-page: https://github.com/OCA/account-invoicing
License: AGPL-3
Author: Open Source Integrators, Serpent CS, Odoo Community Association (OCA)
Author-email: support@odoo-community.org
Classifier: Programming Language :: Python
Classifier: Framework :: Odoo
Classifier: Framework :: Odoo :: 18.0
Classifier: License :: OSI Approved :: GNU Affero General Public License v3
Classifier: Development Status :: 4 - Beta
